{
    "format_version": "1.8.0",
    "animations": {
        "animation.universal.character.fiona.idle": {
            "loop": true,
            "bones": {
                "waist": {
                    "position": [0, "math.cos(query.anim_time * 120) * 0.18", 0]
                },
                "head": {
                    "rotation": ["((math.cos((query.anim_time + 0.87) * 120) * 1))", 0, 0],
                    "position": [0, "((math.cos((query.anim_time + 0.47) * 120) * 0.05))", 0],
                    "scale": 1.01
                },
                "rightArm": {
                    "rotation": [0, 0, "-((math.cos((query.anim_time + 0.77) * 120) * 1)) + 1"],
                    "position": [0, "((math.cos((query.anim_time + 0.27) * 120) * 0.05)) - 0.05", 0]
                },
                "leftArm": {
                    "rotation": [0, 0, "((math.cos((query.anim_time + 0.77) * 120) * 1)) - 1"],
                    "position": [0, "((math.cos((query.anim_time + 0.27) * 120) * 0.05)) - 0.05", 0]
                }
            }
        },
        "animation.universal.character.fiona.head.idle": {
            "animation_length": 8.4,
            "bones": {
                "waist": {
                    "rotation": {
                        "0.04": [0, 0, 0],
                        "0.12": [0, 0.2338, 0],
                        "0.2": [0, 0.3108, 0],
                        "0.28": [0, 0.35, 0],
                        "1.52": [0, 0.35, 0],
                        "1.6": [-0.2338, 0.1162, 0],
                        "1.68": [-0.3108, 0.0392, 0],
                        "1.8": [-0.35, 0, 0],
                        "3.56": [-0.35, 0, 0],
                        "3.64": [-0.525, -0.3374, 0.1778],
                        "3.72": [-0.5824, -0.4494, 0.238],
                        "3.8": [-0.61146, -0.50608, 0.26774],
                        "4.16": [-0.6118, -0.5054, 0.2674],
                        "4.24": [-0.6538, -0.511, 0.1974],
                        "4.32": [-0.6678, -0.5124, 0.1736],
                        "4.4": [-0.67514, -0.51336, 0.16249],
                        "5.52": [-0.6748, -0.5138, 0.1624],
                        "5.6": [-0.098, -0.0434, -0.0168],
                        "5.68": [0.3346, 0.3094, -0.1512],
                        "5.8": [0.4793, 0.42694, -0.1955],
                        "6.76": [0.4788, 0.427, -0.196],
                        "6.84": [0.4788, 0.3402, -0.2016],
                        "6.92": [0.4788, 0.2968, -0.2044],
                        "7.04": [0.47836, 0.25231, -0.20644],
                        "8.08": [0.4788, 0.252, -0.2058],
                        "8.16": [0.2058, 0.1078, -0.0882],
                        "8.24": [0.1232, 0.0644, -0.0532],
                        "8.4": [0, 0, 0]
                    }
                },
                "head": {
                    "rotation": {
                        "0.0": [0, 0, 0],
                        "0.08": [0, 0.668, 0],
                        "0.16": [0, 0.888, 0],
                        "0.24": [0, 1, 0],
                        "1.48": [0, 1, 0],
                        "1.56": [-0.668, 0.332, 0],
                        "1.64": [-0.888, 0.112, 0],
                        "1.76": [-1, 0, 0],
                        "3.52": [-1, 0, 0],
                        "3.6": [-1.5, -0.964, 0.508],
                        "3.68": [-1.664, -1.284, 0.68],
                        "3.76": [-1.74705, -1.44594, 0.76498],
                        "4.12": [-1.748, -1.444, 0.764],
                        "4.2": [-1.868, -1.46, 0.564],
                        "4.28": [-1.908, -1.464, 0.496],
                        "4.36": [-1.92898, -1.46674, 0.46426],
                        "5.48": [-1.928, -1.468, 0.464],
                        "5.56": [-0.28, -0.124, -0.048],
                        "5.64": [0.956, 0.884, -0.432],
                        "5.76": [1.36942, 1.21982, -0.55857],
                        "6.72": [1.368, 1.22, -0.56],
                        "6.8": [1.368, 0.972, -0.576],
                        "6.88": [1.368, 0.848, -0.584],
                        "7.0": [1.36674, 0.72089, -0.58984],
                        "8.04": [1.368, 0.72, -0.588],
                        "8.12": [0.588, 0.308, -0.252],
                        "8.2": [0.352, 0.184, -0.152],
                        "8.36": [0, 0, 0]
                    }
                }
            }
        },
        "animation.universal.character.fiona.fidget": {
            "loop": "hold_on_last_frame",
            "animation_length": 8,
            "bones": {
                "rightLeg": {
                    "rotation": {
                        "0.16": [0, 0, 0],
                        "0.36": [0, 6.94, 0]
                    }
                },
                "leftLeg": {
                    "rotation": {
                        "0.0": [0, 0, 0],
                        "0.16": [5, 0, 0],
                        "0.36": [-3.37, -6.23, 0.55],
                        "0.48": [-5.04292, -7.4713, 0.6574],
                        "6.88": [-5.04, -7.47, 0.66],
                        "6.96": [-3.78, -5.6, 0.5],
                        "7.08": [0, 0, 0]
                    },
                    "position": {
                        "0.0": [0, 0, 0],
                        "0.16": [0, 0, -0.95],
                        "0.36": [0.25, 0.4, -1.2],
                        "0.48": [0.3, 0, -1.25],
                        "6.88": [0.3, 0, -1.25],
                        "6.96": [0.22, 0, -0.94],
                        "7.08": [0, 0, 0]
                    }
                },
                "waist": {
                    "rotation": {
                        "0.0": [0, 0, 0],
                        "0.08": [1.5, 0, 0],
                        "0.24": [2.25, 0, 0],
                        "0.36": [-2.06, 0, 0],
                        "0.48": [-3.14, 0, 0],
                        "0.6": [-3.5, 0, 0],
                        "1.8": [-3.5, 0, 0],
                        "1.96": [-3.5, 1.6, -0.1],
                        "2.12": [-3.50213, 1.99627, -0.12215],
                        "3.72": [-3.5, 2, -0.12],
                        "4.68": [-3.5, 2, -0.12],
                        "5.04": [-3.241, 2.39731, 6.62328],
                        "5.56": [-3.19, 2.46, 7.73],
                        "5.88": [-3.18, 2.47, 7.95],
                        "6.12": [-3.18, 2.48, 8.04],
                        "6.4": [-3.1772, 2.48128, 8.12229],
                        "6.88": [-3.18, 2.48, 8.12],
                        "6.96": [-2.39, 1.86, 6.28],
                        "7.04": [0, 0, 0.75],
                        "7.12": [0, 0, 0.23],
                        "7.2": [0, 0, 0]
                    },
                    "position": {
                        "0.0": [0, 0, 0],
                        "0.12": [0, -0.25, -0.325],
                        "0.28": [0, -0.81, -0.58],
                        "0.36": [0, -0.27, -0.71],
                        "0.48": [0, -0.07, -0.76],
                        "0.6": [0, 0, -0.775],
                        "0.68": [0, -0.08, -0.77],
                        "0.76": [0, -0.125, -0.77],
                        "1.8": [0, -0.12, -0.77],
                        "3.72": [0, -0.12, -0.77],
                        "4.68": [0, -0.12, -0.77],
                        "4.84": [0.64, -1.245, -0.77],
                        "5.04": [1.25, -0.27, -0.77],
                        "5.16": [1.25, -0.645, -0.77],
                        "5.28": [1.25, -0.515, -0.77],
                        "5.56": [1.33, -0.51, -0.77],
                        "5.88": [1.36, -0.51, -0.77],
                        "6.12": [1.37, -0.51, -0.77],
                        "6.4": [1.375, -0.51, -0.77],
                        "6.88": [1.38, -0.51, -0.77],
                        "6.96": [1.03, -0.55, -0.58],
                        "7.04": [0, -0.675, 0],
                        "7.12": [0, -0.01, 0],
                        "7.2": [0, 0.275, 0],
                        "7.28": [0, -0.125, 0],
                        "7.4": [0, 0, 0]
                    }
                },
                "head": {
                    "rotation": {
                        "0.0": [0, 0, 0],
                        "0.16": [2.75, 0, 0],
                        "0.24": [5.75, 0, 0],
                        "0.32": [7.25, 0, 0],
                        "0.44": [-1.19, 0, 0],
                        "0.56": [-3.3, 0, 0],
                        "0.68": [-4, 0, 0],
                        "0.8": [-1.75, 0, 0],
                        "0.92": [-2.5, 0, 0],
                        "1.68": [-2.5, 0, 0],
                        "1.76": [-2.51, 3.7, -0.16],
                        "1.88": [-2.53, 7.86, -0.35],
                        "2.04": [-2.53289, 9.24112, -0.40701],
                        "3.72": [-2.53, 9.24, -0.41],
                        "3.84": [-1.44, 8.6, -0.44],
                        "3.96": [3.48, 5.71, -0.56],
                        "4.04": [4.3, 5.23, -0.58],
                        "4.12": [4.84, 4.91, -0.59],
                        "4.24": [5.11617, 4.7448, -0.5978],
                        "6.88": [5.12, 4.74, -0.6],
                        "7.04": [5.25, 0, 0],
                        "7.28": [0, 0, 0],
                        "7.44": [1.75, 0, 0],
                        "7.6": [0.44, 0, 0],
                        "7.76": [0, 0, 0]
                    },
                    "position": {
                        "0.0": [0, 0, 0],
                        "6.88": [0, 0, 0],
                        "7.04": [0, -0.15, 0],
                        "7.28": [0, 0.15, 0],
                        "7.56": [0, 0, 0]
                    }
                },
                "rightArm": {
                    "rotation": {
                        "0.0": [0, 0, 0],
                        "0.16": [-2.32, -1.03, -0.29],
                        "0.28": [-16.21, -7.2, -2.01],
                        "0.44": [-18.90016, -15.15419, -22.74574],
                        "3.72": [-18.9, -15.15, -22.75],
                        "3.84": [-17.81, -15.08, -22.54],
                        "4.0": [-11.27732, -14.65943, -21.28313],
                        "4.68": [-11.28, -14.66, -21.28],
                        "4.8": [-84.37745, -2.09787, 50.39697],
                        "4.92": [-74.6451, 52.68466, 60.20769],
                        "5.08": [-6.10524, 79.69532, 134.11351],
                        "5.2": [12.46, 79.7, 134.11],
                        "5.32": [18.64476, 79.69532, 134.11351],
                        "5.44": [-2.15, 79.7, 134.11],
                        "5.56": [-6.10524, 79.69532, 134.11351],
                        "5.64": [0.08, 79.7, 134.11],
                        "5.72": [12.46, 79.7, 134.11],
                        "5.84": [18.64476, 79.69532, 134.11351],
                        "5.96": [6.08, 79.7, 134.11],
                        "6.08": [1.89476, 79.69532, 134.11351],
                        "6.24": [9.14476, 79.69532, 134.11351],
                        "6.4": [6.64476, 79.69532, 134.11351],
                        "6.88": [6.64, 79.7, 134.11],
                        "7.04": [0, 0, 0],
                        "7.2": [0, 0, -0.546],
                        "7.28": [0, 0, -0.6825],
                        "7.4": [0, 0, 0]
                    },
                    "position": {
                        "0.0": [0, 0, 0],
                        "0.16": [0.1, -0.12, -0.21],
                        "0.28": [0.73, -0.875, -1.5],
                        "0.44": [1, 0, -2.05],
                        "0.6": [1, 0.35, -2.05],
                        "0.68": [1, 0.11, -2.05],
                        "0.76": [1, -0.25, -2.05],
                        "0.84": [1, -0.18, -2.05],
                        "0.92": [1, -0.15, -2.05],
                        "3.72": [1, -0.15, -2.05],
                        "3.84": [0.98, -0.21, -2.05],
                        "4.0": [0.875, -0.55, -2.05],
                        "4.12": [0.87, -0.325, -2.05],
                        "4.2": [0.87, -0.37, -2.05],
                        "4.32": [0.87, -0.4, -2.05],
                        "4.68": [0.87, -0.4, -2.05],
                        "4.8": [0, 0, 0],
                        "6.88": [0, 0, 0],
                        "7.04": [0, 0, 0],
                        "7.2": [0, 0.26, 0],
                        "7.28": [0, 0.325, 0],
                        "7.4": [0, -0.2, 0],
                        "7.48": [0, -0.07, 0],
                        "7.56": [0, 0, 0]
                    }
                },
                "leftArm": {
                    "rotation": {
                        "0.0": [0, 0, 0],
                        "0.16": [-2.32, 1.03, 0.29],
                        "0.28": [-16.21, 7.2, 2.01],
                        "0.44": [-18.90016, 15.15419, 22.74574],
                        "3.72": [-18.9, 15.15, 22.75],
                        "3.84": [-17.81, 15.08, 22.54],
                        "4.0": [-11.27732, 14.65943, 21.28313],
                        "4.68": [-11.28, 14.66, 21.28],
                        "4.76": [-9.28, 13.44, 16.68],
                        "4.84": [0.06, 7.75, -4.8],
                        "5.0": [4.7227, 4.90963, -15.53266],
                        "6.88": [4.72, 4.91, -15.53],
                        "7.04": [0, 0, 0],
                        "7.2": [0, 0, -0.546],
                        "7.28": [0, 0, -0.6825],
                        "7.4": [0, 0, 0]
                    },
                    "position": {
                        "0.0": [0, 0, 0],
                        "0.16": [-0.1, -0.12, -0.21],
                        "0.28": [-0.73, -0.875, -1.5],
                        "0.44": [-1, 0, -2.05],
                        "0.6": [-1, 0.35, -2.05],
                        "0.68": [-1, 0.11, -2.05],
                        "0.76": [-1, -0.25, -2.05],
                        "0.84": [-1, -0.18, -2.05],
                        "0.92": [-1, -0.15, -2.05],
                        "3.72": [-1, -0.15, -2.05],
                        "3.84": [-0.98, -0.21, -2.05],
                        "4.0": [-0.875, -0.55, -2.05],
                        "4.12": [-0.87, -0.325, -2.05],
                        "4.2": [-0.87, -0.37, -2.05],
                        "4.32": [-0.87, -0.4, -2.05],
                        "4.68": [-0.87, -0.4, -2.05],
                        "4.76": [-0.78, -0.52, -1.55],
                        "4.84": [-0.34, -1.11, 0.78],
                        "5.0": [-0.12, -1.4, 1.95],
                        "6.88": [-0.12, -1.4, 1.95],
                        "7.04": [0, 0, 0],
                        "7.2": [0, 0.26, 0],
                        "7.28": [0, 0.325, 0],
                        "7.4": [0, -0.2, 0],
                        "7.48": [0, -0.07, 0],
                        "7.56": [0, 0, 0]
                    }
                }
            }
        },
        "animation.universal.character.fiona.sing": {
            "loop": "hold_on_last_frame",
            "animation_length": 5.48,
            "bones": {
                "rightLeg": {
                    "rotation": {
                        "0.0": [0, 0, 0],
                        "0.08": [-0.28, 1.67, 0],
                        "0.2": [-2.22, 13.33, 0],
                        "0.32": [-2.5, 15, 0],
                        "4.68": [-2.5, 15, 0],
                        "4.76": [-2.29, 13.75, 0],
                        "4.88": [-0.46, 2.75, 0],
                        "5.0": [0, 0, 0]
                    },
                    "position": {
                        "0.0": [0, 0, 0],
                        "0.08": [0.03, 0, 0.06],
                        "0.2": [0.22, 0, 0.45],
                        "0.32": [0.25, 0, 0.5],
                        "4.68": [0.25, 0, 0.5],
                        "4.76": [0.23, 0, 0.46],
                        "4.88": [0.05, 0, 0.09],
                        "5.0": [0, 0, 0]
                    }
                },
                "leftLeg": {
                    "rotation": {
                        "0.0": [0, 0, 0],
                        "0.08": [1.21, 2.06, -0.57],
                        "0.2": [9.7, 16.46, -4.58],
                        "0.32": [10.90741, 18.51497, -5.14833],
                        "4.68": [10.91, 18.51, -5.15],
                        "4.76": [10, 16.97, -4.72],
                        "4.88": [2, 3.39, -0.94],
                        "5.0": [0, 0, 0]
                    },
                    "position": {
                        "0.0": [0, 0, 0],
                        "0.08": [0.22, 0, -0.11],
                        "0.2": [1.78, 0, -0.89],
                        "0.32": [2, 0, -1],
                        "4.68": [2, 0, -1],
                        "4.76": [1.83, 0, -0.92],
                        "4.88": [0.37, 0, -0.18],
                        "5.0": [0, 0, 0]
                    }
                },
                "waist": {
                    "rotation": {
                        "0.0": [0, 0, 0],
                        "0.24": [-6.43, 12.86, 0],
                        "0.36": [-7.23, 14.47, 0],
                        "0.52": [-7.5, 15, 0],
                        "0.88": [-7.5, 15, 0],
                        "0.96": [-3.75, 15, 0],
                        "1.08": [-2.25, 15, 0],
                        "1.16": [-1.88, 15, 0],
                        "1.28": [-0.47, 15, 0],
                        "1.4": [0, 15, 0],
                        "1.48": [-1.3, 15, 0],
                        "1.56": [-1.9, 15, 0],
                        "1.68": [-2.26, 15, 0],
                        "1.8": [-2.44, 15, 0],
                        "1.88": [-2.5, 15, 0],
                        "1.96": [-2.05, 15, 0],
                        "2.04": [-1.9, 15, 0],
                        "2.12": [-2, 15, 0],
                        "2.2": [-2.05, 15, 0],
                        "4.68": [-2.05, 15, 0],
                        "4.76": [-1.71, 12.5, 0],
                        "4.88": [-0.43, 3.13, 0],
                        "5.0": [0, 0, 0]
                    },
                    "position": {
                        "0.0": [0, 0, 0],
                        "0.04": [0.27, -0.425, 0.16],
                        "0.16": [1.6, -0.875, 0.98],
                        "0.24": [1.87, -0.29, 1.14],
                        "0.36": [1.97, -0.07, 1.2],
                        "0.52": [2, 0, 1.225],
                        "0.88": [2, 0, 1.23],
                        "0.96": [1.81, -0.67, 0.78],
                        "1.08": [1.74, -0.93, 0.6],
                        "1.16": [1.72, -1, 0.56],
                        "1.28": [1.65, -0.7, 0.39],
                        "1.4": [1.625, -0.6, 0.33],
                        "1.48": [1.63, -0.67, 0.33],
                        "1.56": [1.63, -0.06, 0.33],
                        "1.68": [1.63, 0.31, 0.33],
                        "1.8": [1.63, 0.49, 0.33],
                        "1.88": [1.63, 0.55, 0.33],
                        "1.96": [1.63, 0.09, 0.33],
                        "2.04": [1.63, -0.06, 0.33],
                        "2.12": [1.63, 0.04, 0.33],
                        "2.2": [1.63, 0.09, 0.33],
                        "4.68": [1.63, 0.09, 0.33],
                        "4.76": [1.36, 0.08, 0.28],
                        "4.88": [0.34, -0.455, 0.07],
                        "5.0": [0, 0, 0],
                        "5.08": [0, -0.125, 0],
                        "5.16": [0, -0.04, 0],
                        "5.24": [0, -0.01, 0],
                        "5.32": [0, 0, 0]
                    }
                },
                "head": {
                    "rotation": {
                        "0.0": [0, 0, 0],
                        "0.12": [7, 0, 0],
                        "0.28": [-3.5, 0, 0],
                        "0.4": [-6.12, 0, 0],
                        "0.48": [-6.71, 0, 0],
                        "0.6": [-7, 0, 0],
                        "0.8": [-7, 0, 0],
                        "0.88": [-8.25, 0, 0],
                        "0.96": [-2.75, 0, 0],
                        "1.04": [0, 0, 0],
                        "1.16": [7.75, 0, 0],
                        "1.24": [2.62, 0, 0],
                        "1.32": [0.06, 0, 0],
                        "1.44": [-2.5, 0, 0],
                        "1.52": [7.25, 0, 0],
                        "1.6": [3.2, 0, 0],
                        "1.64": [-7.6, 0, 0],
                        "1.76": [-11.65, 0, 0],
                        "1.92": [-12.73, 0, 0],
                        "2.12": [-1.48, 0, 0],
                        "2.24": [-2.48, 0, 0],
                        "2.68": [-2.48, 0, 0],
                        "2.76": [-2.68, 0.33, 0.29],
                        "2.84": [-3.08, 1, 0.87],
                        "2.96": [-5.01, 4.23, 3.66],
                        "3.04": [-5.4, 4.87, 4.22],
                        "3.12": [-5.65, 5.3, 4.59],
                        "3.24": [-5.78163, 5.5192, 4.77661],
                        "3.88": [-5.78, 5.52, 4.78],
                        "3.92": [-5.79, 4.94, 4.49],
                        "4.0": [-5.83, 3.19, 3.61],
                        "4.08": [-5.84, 2.8, 3.41],
                        "4.16": [-5.8419, 2.60704, 3.31421],
                        "4.68": [-5.84, 2.61, 3.31],
                        "4.8": [5.92, -1.17, 0.94],
                        "4.92": [9.84055, -2.43392, 0.14949],
                        "5.08": [-1.75, 0, 0],
                        "5.2": [0.75, 0, 0],
                        "5.32": [0.3, 0, 0],
                        "5.48": [0, 0, 0]
                    },
                    "position": {
                        "0.0": [0, 0, 0],
                        "0.12": [0.1, 0, 0],
                        "0.88": [0.1, 0, 0],
                        "1.08": [0.1, -0.65, 0],
                        "1.52": [0.1, -0.65, 0],
                        "1.68": [0.1, 0.39, 0],
                        "1.76": [0.1, 0.65, 0],
                        "1.92": [0.1, 0.65, 0],
                        "2.04": [0, 0, 0]
                    }
                },
                "rightArm": {
                    "rotation": {
                        "0.0": [0, 0, 0],
                        "0.2": [19.99294, -0.32621, 12.47864],
                        "0.32": [22.99, -0.33, 12.48],
                        "0.48": [23.94, -0.33, 12.48],
                        "0.64": [24.25, -0.33, 12.48],
                        "0.84": [24.49, -0.33, 12.48],
                        "0.88": [24.49, -0.33, 12.48],
                        "0.96": [2.72, -0.04, 5.83],
                        "1.08": [0, 0, 5],
                        "1.16": [0, 0, 5],
                        "1.2": [-0.5, 0, 7.5],
                        "1.28": [-2, 0, 15],
                        "1.36": [-2.33, 0, 16.67],
                        "1.44": [-2.5, 0, 17.5],
                        "1.52": [0.27281, -0.33702, 9.75729],
                        "1.6": [0.2, -0.36, 19.41],
                        "1.64": [-0.02, -0.42, 51.57],
                        "1.76": [-0.06, -0.43, 56.4],
                        "1.88": [-0.06979, -0.42794, 58.00835],
                        "1.92": [-0.08839, -0.42449, 60.50842],
                        "2.04": [0.04, -0.43, 43.42],
                        "2.12": [0.06587, -0.42856, 40.00784],
                        "2.16": [0.06, -0.43, 40.88],
                        "2.24": [0.06, -0.43, 41.47],
                        "2.32": [0.05276, -0.43038, 41.75789],
                        "4.68": [0.05, -0.43, 41.76],
                        "4.76": [-0.29, -0.43, 36.46],
                        "4.88": [-1.9937, -0.41734, 9.98147],
                        "4.92": [-1, -0.21, 4.99],
                        "5.0": [0, 0, 0]
                    },
                    "position": {
                        "0.0": [0, 0, 0],
                        "0.2": [0, 0, 0],
                        "0.32": [0, 0.38, 0],
                        "0.48": [0, 0.5, 0],
                        "0.64": [0, 0.54, 0],
                        "0.84": [0, 0.575, 0],
                        "0.88": [0, 0.57, 0],
                        "0.96": [0, 0.06, 0],
                        "1.08": [0, 0, 0],
                        "1.16": [0, 0, 0],
                        "1.2": [0, 0.03, 0],
                        "1.28": [0, 0.12, 0],
                        "1.36": [0, 0.14, 0],
                        "1.44": [0, 0.15, 0],
                        "4.68": [0, 0.15, 0],
                        "4.76": [0, 0.03, 0],
                        "4.88": [0, -0.595, 0],
                        "4.92": [0, -0.3, 0],
                        "5.0": [0, 0, 0]
                    }
                },
                "leftArm": {
                    "rotation": {
                        "0.0": [0, 0, 0],
                        "0.2": [19.99294, 0.32621, -12.47864],
                        "0.32": [22.99, 0.33, -12.48],
                        "0.48": [23.94, 0.33, -12.48],
                        "0.64": [24.25, 0.33, -12.48],
                        "0.84": [24.49, 0.33, -12.48],
                        "0.88": [24.49, 0.33, -12.48],
                        "0.96": [2.72, 0.04, -5.83],
                        "1.08": [0, 0, -5],
                        "1.16": [0, 0, -5],
                        "1.2": [-0.5, 0, -7.5],
                        "1.28": [-2, 0, -15],
                        "1.36": [-2.33, 0, -16.67],
                        "1.44": [-2.5, 0, -17.5],
                        "1.52": [0.27281, 0.33702, -9.75729],
                        "1.6": [0.2, 0.36, -19.41],
                        "1.64": [-0.02, 0.42, -51.57],
                        "1.76": [-0.06, 0.43, -56.4],
                        "1.88": [-0.06979, 0.42794, -58.00835],
                        "1.92": [-0.08839, 0.42449, -60.50842],
                        "2.0": [0.04, 0.43, -43.42],
                        "2.08": [0.06587, 0.42856, -40.00784],
                        "2.12": [0.06, 0.43, -40.88],
                        "2.2": [0.06, 0.43, -41.47],
                        "2.28": [0.05276, 0.43038, -41.75789],
                        "4.68": [0.05, 0.43, -41.76],
                        "4.76": [-0.29, 0.43, -36.46],
                        "4.88": [-1.9937, 0.41734, -9.98147],
                        "4.92": [-1, 0.21, -4.99],
                        "5.0": [0, 0, 0]
                    },
                    "position": {
                        "0.0": [0, 0, 0],
                        "0.2": [0, 0, 0],
                        "0.32": [0, 0.38, 0],
                        "0.48": [0, 0.5, 0],
                        "0.64": [0, 0.54, 0],
                        "0.84": [0, 0.575, 0],
                        "0.88": [0, 0.57, 0],
                        "0.96": [0, 0.06, 0],
                        "1.08": [0, 0, 0],
                        "1.16": [0, 0, 0],
                        "1.2": [0, 0.03, 0],
                        "1.28": [0, 0.12, 0],
                        "1.36": [0, 0.14, 0],
                        "1.44": [0, 0.15, 0],
                        "4.68": [0, 0.15, 0],
                        "4.76": [0, 0.03, 0],
                        "4.88": [0, -0.595, 0],
                        "4.92": [0, -0.3, 0],
                        "5.0": [0, 0, 0]
                    }
                },
                "notes": {
                    "rotation": [0, 0, 0],
                    "position": {
                        "0.92": [0, 0, 0],
                        "4.04": [0, 3.375, 0]
                    }
                },
                "note1": {
                    "rotation": {
                        "1.52": [0, 0, 0],
                        "1.64": [0, 0, "math.cos(query.anim_time * 260) * 7"],
                        "3.88": [0, 0, 0]
                    },
                    "position": {
                        "1.52": [0, 40, 0],
                        "1.56": [-0.01006, 40.30978, 0],
                        "1.6": [-0.02383, 40.84132, 0],
                        "1.64": [-0.03856, 41.29277, 0],
                        "1.68": [-0.05379, 41.67159, 0],
                        "1.72": [-0.06935, 41.99885, 0],
                        "1.76": [-0.08514, 42.2883, 0],
                        "1.8": [-0.10111, 42.54871, 0],
                        "1.84": [-0.11721, 42.78586, 0],
                        "1.88": [-0.13342, 43.00399, 0],
                        "1.92": [-0.14971, 43.20596, 0],
                        "1.96": [-0.16609, 43.39424, 0],
                        "2.0": [-0.18253, 43.57061, 0],
                        "2.16": [-0.24876, 44.18128, 0],
                        "2.4": [-0.34901, 44.89696, 0],
                        "2.76": [-0.50022, 45.68587, 0],
                        "3.28": [-0.71786, 46.45476, 0],
                        "3.8": [-0.92617, 46.94333, 0],
                        "3.88": [-0.95, 47, 0]
                    },
                    "scale": {
                        "1.52": [0, 0, 1],
                        "1.64": [0.9188, 0.9188, 1],
                        "1.68": [1.0063, 1.0063, 1],
                        "1.72": [1.05, 1.05, 1],
                        "1.8": [1.04, 1.04, 1],
                        "1.88": [1.0133, 1.0133, 1],
                        "1.92": [1.0044, 1.0044, 1],
                        "2.0": [1, 1, 1],
                        "3.56": [1, 1, 1],
                        "3.64": [0.9778, 0.9778, 1],
                        "3.68": [0.9333, 0.9333, 1],
                        "3.8": [0.6, 0.6, 1],
                        "3.88": [0, 0, 1]
                    }
                },
                "note2": {
                    "rotation": {
                        "0.92": [0, 0, 0],
                        "1.04": [0, 0, "math.cos(query.anim_time * 250) * 7"],
                        "3.52": [0, 0, 0]
                    },
                    "position": {
                        "0.92": [0, 40, 0],
                        "0.96": [-0.00931, 40.19889, 0],
                        "1.04": [-0.03523, 40.8715, 0],
                        "1.08": [-0.04903, 41.18147, 0],
                        "1.12": [-0.06312, 41.46665, 0],
                        "1.16": [-0.0774, 41.72991, 0],
                        "1.2": [-0.09183, 41.97428, 0],
                        "1.24": [-0.10638, 42.20226, 0],
                        "1.28": [-0.12102, 42.41598, 0],
                        "1.32": [-0.13574, 42.61714, 0],
                        "1.36": [-0.15052, 42.80715, 0],
                        "1.52": [-0.21014, 43.47608, 0],
                        "1.76": [-0.3005, 44.27933, 0],
                        "2.08": [-0.42181, 45.10106, 0],
                        "2.56": [-0.60408, 45.98644, 0],
                        "3.08": [-0.79948, 46.63279, 0],
                        "3.48": [-0.94069, 46.97222, 0],
                        "3.52": [-0.95, 47, 0]
                    },
                    "scale": {
                        "0.92": [0, 0, 1],
                        "1.04": [0.9188, 0.9188, 1],
                        "1.08": [1.0063, 1.0063, 1],
                        "1.12": [1.05, 1.05, 1],
                        "1.2": [1.04, 1.04, 1],
                        "1.28": [1.0133, 1.0133, 1],
                        "1.32": [1.0044, 1.0044, 1],
                        "1.4": [1, 1, 1],
                        "3.2": [1, 1, 1],
                        "3.28": [0.9778, 0.9778, 1],
                        "3.32": [0.9333, 0.9333, 1],
                        "3.44": [0.6, 0.6, 1],
                        "3.52": [0, 0, 1]
                    }
                },
                "note3": {
                    "rotation": {
                        "1.16": [0, 0, 0],
                        "1.28": [0, 0, "math.cos(query.anim_time * 240) * 7"],
                        "3.64": [0, 0, 0]
                    },
                    "position": {
                        "1.16": [0, 40, 0],
                        "1.2": [-0.00967, 40.24122, 0],
                        "1.24": [-0.0228, 40.65857, 0],
                        "1.28": [-0.03681, 41.04916, 0],
                        "1.32": [-0.0513, 41.39581, 0],
                        "1.36": [-0.06609, 41.70527, 0],
                        "1.4": [-0.08108, 41.98491, 0],
                        "1.44": [-0.09624, 42.24033, 0],
                        "1.48": [-0.11152, 42.47565, 0],
                        "1.52": [-0.12691, 42.69398, 0],
                        "1.56": [-0.14238, 42.89778, 0],
                        "1.6": [-0.15791, 43.08886, 0],
                        "1.76": [-0.22059, 43.75253, 0],
                        "1.96": [-0.29969, 44.41775, 0],
                        "2.28": [-0.42711, 45.234, 0],
                        "2.76": [-0.61853, 46.09421, 0],
                        "3.28": [-0.82309, 46.7094, 0],
                        "3.6": [-0.94033, 46.97221, 0],
                        "3.64": [-0.95, 47, 0]
                    },
                    "scale": {
                        "1.16": [0, 0, 1],
                        "1.28": [0.9188, 0.9188, 1],
                        "1.32": [1.0063, 1.0063, 1],
                        "1.36": [1.05, 1.05, 1],
                        "1.44": [1.04, 1.04, 1],
                        "1.52": [1.0133, 1.0133, 1],
                        "1.56": [1.0044, 1.0044, 1],
                        "1.64": [1, 1, 1],
                        "3.32": [1, 1, 1],
                        "3.4": [0.9778, 0.9778, 1],
                        "3.44": [0.9333, 0.9333, 1],
                        "3.56": [0.6, 0.6, 1],
                        "3.64": [0, 0, 1]
                    }
                }
            }
        },
        "animation.universal.character.fiona.look.around": {
            "animation_length": 12,
            "bones": {
                "head": {
                    "rotation": {
                        "0.6": [0, 0, 0],
                        "0.88": [2.1, -4.88, -0.25],
                        "1.0": [2.55, -5.93, -0.31],
                        "1.08": [2.69771, -6.27683, -0.32593],
                        "2.68": [2.6975, -6.2775, -0.325],
                        "2.88": [2.23, -6.28, -0.32],
                        "2.96": [2.13, -6.28, -0.32],
                        "3.08": [2.0725, -6.2775, -0.325],
                        "4.64": [2.0725, -6.2775, -0.325],
                        "4.8": [2.07, -4.46, -0.43],
                        "4.92": [2.06, -3.64, -0.47],
                        "5.08": [2.06089, -3.09591, -0.50078],
                        "6.24": [2.06, -3.095, -0.5],
                        "6.48": [1.57, -0.86, -0.17],
                        "6.64": [1.39, -0.01, -0.04],
                        "6.84": [1.25119, 0.62262, 0.05451],
                        "7.52": [1.25119, 0.62262, 0.05451],
                        "7.76": [0.42, 0.21, 0.02],
                        "7.92": [0.14, 0.07, 0.01],
                        "8.24": [0, 0, 0]
                    }
                }
            }
        }
    }
}
